CheeseAgent/__init__.py
CheeseAgent/agent.py
CheeseAgent-0.0.1.dist-info/METADATA
CheeseAgent-0.0.1.dist-info/WHEEL
CheeseAgent-0.0.1.dist-info/top_level.txt
CheeseAgent-0.0.1.dist-info/RECORD
