Metadata-Version: 2.1
Name: CheeseAgent
Version: 0.0.1
Summary: An easy way to import your additional packages for Rocket League Python bot development
Author: JoshyDev
Author-email: <iamjoshydev@gmail.com>
Keywords: python,ai,development,bot building,rocket league,rlbot
Classifier: Development Status :: 1 - Planning
Classifier: Intended Audience :: Developers
Classifier: Programming Language :: Python :: 3
Classifier: Operating System :: Unix
Classifier: Operating System :: MacOS :: MacOS X
Classifier: Operating System :: Microsoft :: Windows
